odoo10_addon_cms_delete_content_example-10.0.1.0.0-py2.7-nspkg.pth
odoo/addons/cms_delete_content_example/README.rst
odoo/addons/cms_delete_content_example/__init__.py
odoo/addons/cms_delete_content_example/__manifest__.py
odoo/addons/cms_delete_content_example/controllers/__init__.py
odoo/addons/cms_delete_content_example/controllers/main.py
odoo/addons/cms_delete_content_example/data/examples.xml
odoo/addons/cms_delete_content_example/data/ir.model.access.csv
odoo/addons/cms_delete_content_example/models/__init__.py
odoo/addons/cms_delete_content_example/models/example.py
odoo/addons/cms_delete_content_example/static/description/icon.png
odoo/addons/cms_delete_content_example/templates/example.xml
odoo10_addon_cms_delete_content_example-10.0.1.0.0.dist-info/DESCRIPTION.rst
odoo10_addon_cms_delete_content_example-10.0.1.0.0.dist-info/METADATA
odoo10_addon_cms_delete_content_example-10.0.1.0.0.dist-info/RECORD
odoo10_addon_cms_delete_content_example-10.0.1.0.0.dist-info/WHEEL
odoo10_addon_cms_delete_content_example-10.0.1.0.0.dist-info/metadata.json
odoo10_addon_cms_delete_content_example-10.0.1.0.0.dist-info/namespace_packages.txt
odoo10_addon_cms_delete_content_example-10.0.1.0.0.dist-info/top_level.txt
